{
  "generated_at": "2025-12-28T17:32:41.592375",
  "radar": [
    {
      "angle": 194,
      "dist": 40,
      "type": "HOSTILE"
    },
    {
      "angle": 279,
      "dist": 50,
      "type": "HOSTILE"
    },
    {
      "angle": 296,
      "dist": 44,
      "type": "HOSTILE"
    },
    {
      "angle": 111,
      "dist": 26,
      "type": "UNKNOWN"
    },
    {
      "angle": 258,
      "dist": 43,
      "type": "HOSTILE"
    }
  ],
  "logs": [
    "[17:32:41] main/wp-content process_id=6591 status=SYNC",
    "[17:32:41] list/explore/app process_id=3972 status=SYNC",
    "[17:32:41] categories/wp-content process_id=7784 status=SYNC",
    "[17:32:41] search process_id=9525 status=SYNC",
    "[17:32:41] main process_id=2643 status=SYNC",
    "[17:32:41] category process_id=2726 status=SYNC",
    "[17:32:41] tag/app process_id=3908 status=SYNC",
    "[17:32:41] wp-content process_id=7174 status=SYNC",
    "[17:32:41] tag process_id=2074 status=SYNC",
    "[17:32:41] blog process_id=5480 status=SYNC",
    "[17:32:41] main/search process_id=8128 status=SYNC",
    "[17:32:41] wp-content/blog process_id=2997 status=SYNC",
    "[17:32:41] posts/wp-content/explore process_id=9115 status=SYNC",
    "[17:32:41] posts/category process_id=3796 status=SYNC",
    "[17:32:41] app/tags/app process_id=6386 status=SYNC",
    "[17:32:41] main/wp-content process_id=1405 status=SYNC",
    "[17:32:41] explore/tags process_id=6079 status=SYNC",
    "[17:32:41] wp-content/main/tag process_id=8100 status=SYNC",
    "[17:32:41] main process_id=8597 status=SYNC",
    "[17:32:41] search process_id=8913 status=SYNC"
  ],
  "nodes": [
    {
      "id": "TER-FUS-000",
      "sector": "EARTH-CORE",
      "color": "blue",
      "service": "Fusion-Reactor",
      "status": "ACTIVE",
      "metrics": {
        "integrity": 94,
        "energy": 2862,
        "temp": 534
      },
      "fw_version": "v10.1"
    },
    {
      "id": "TER-DEF-001",
      "sector": "EARTH-CORE",
      "color": "blue",
      "service": "Defense-Grid",
      "status": "ACTIVE",
      "metrics": {
        "integrity": 97,
        "energy": 2643,
        "temp": 130
      },
      "fw_version": "v12.9"
    },
    {
      "id": "TER-FUS-002",
      "sector": "EARTH-CORE",
      "color": "blue",
      "service": "Fusion-Reactor",
      "status": "ACTIVE",
      "metrics": {
        "integrity": 96,
        "energy": 566,
        "temp": 896
      },
      "fw_version": "v11.8"
    },
    {
      "id": "TER-DEF-003",
      "sector": "EARTH-CORE",
      "color": "blue",
      "service": "Defense-Grid",
      "status": "ACTIVE",
      "metrics": {
        "integrity": 100,
        "energy": 4671,
        "temp": 836
      },
      "fw_version": "v11.2"
    },
    {
      "id": "TER-AI--004",
      "sector": "EARTH-CORE",
      "color": "blue",
      "service": "AI-Cortex",
      "status": "ACTIVE",
      "metrics": {
        "integrity": 98,
        "energy": 4843,
        "temp": 843
      },
      "fw_version": "v10.3"
    },
    {
      "id": "TER-QUA-005",
      "sector": "EARTH-CORE",
      "color": "blue",
      "service": "Quantum-Net",
      "status": "ACTIVE",
      "metrics": {
        "integrity": 94,
        "energy": 2375,
        "temp": 841
      },
      "fw_version": "v11.3"
    },
    {
      "id": "TER-AI--006",
      "sector": "EARTH-CORE",
      "color": "blue",
      "service": "AI-Cortex",
      "status": "ACTIVE",
      "metrics": {
        "integrity": 97,
        "energy": 287,
        "temp": 373
      },
      "fw_version": "v11.1"
    },
    {
      "id": "TER-LIF-007",
      "sector": "EARTH-CORE",
      "color": "blue",
      "service": "Life-Support",
      "status": "CRITICAL",
      "metrics": {
        "integrity": 80,
        "energy": 3618,
        "temp": 256
      },
      "fw_version": "v10.0"
    },
    {
      "id": "TER-FUS-008",
      "sector": "EARTH-CORE",
      "color": "blue",
      "service": "Fusion-Reactor",
      "status": "ACTIVE",
      "metrics": {
        "integrity": 93,
        "energy": 1675,
        "temp": 206
      },
      "fw_version": "v10.3"
    },
    {
      "id": "TER-FUS-009",
      "sector": "EARTH-CORE",
      "color": "blue",
      "service": "Fusion-Reactor",
      "status": "ACTIVE",
      "metrics": {
        "integrity": 98,
        "energy": 2815,
        "temp": 341
      },
      "fw_version": "v11.5"
    },
    {
      "id": "TER-AI--010",
      "sector": "EARTH-CORE",
      "color": "blue",
      "service": "AI-Cortex",
      "status": "ACTIVE",
      "metrics": {
        "integrity": 92,
        "energy": 1679,
        "temp": 791
      },
      "fw_version": "v11.6"
    },
    {
      "id": "TER-LIF-011",
      "sector": "EARTH-CORE",
      "color": "blue",
      "service": "Life-Support",
      "status": "ACTIVE",
      "metrics": {
        "integrity": 97,
        "energy": 849,
        "temp": 490
      },
      "fw_version": "v12.9"
    },
    {
      "id": "TER-DEF-012",
      "sector": "EARTH-CORE",
      "color": "blue",
      "service": "Defense-Grid",
      "status": "ACTIVE",
      "metrics": {
        "integrity": 100,
        "energy": 4700,
        "temp": 882
      },
      "fw_version": "v10.0"
    },
    {
      "id": "TER-DEF-013",
      "sector": "EARTH-CORE",
      "color": "blue",
      "service": "Defense-Grid",
      "status": "ACTIVE",
      "metrics": {
        "integrity": 100,
        "energy": 2077,
        "temp": 700
      },
      "fw_version": "v12.9"
    },
    {
      "id": "TER-FUS-014",
      "sector": "EARTH-CORE",
      "color": "blue",
      "service": "Fusion-Reactor",
      "status": "ACTIVE",
      "metrics": {
        "integrity": 90,
        "energy": 1404,
        "temp": 257
      },
      "fw_version": "v12.3"
    },
    {
      "id": "TER-FUS-015",
      "sector": "EARTH-CORE",
      "color": "blue",
      "service": "Fusion-Reactor",
      "status": "ACTIVE",
      "metrics": {
        "integrity": 90,
        "energy": 2700,
        "temp": 238
      },
      "fw_version": "v10.3"
    },
    {
      "id": "TER-AI--016",
      "sector": "EARTH-CORE",
      "color": "blue",
      "service": "AI-Cortex",
      "status": "ACTIVE",
      "metrics": {
        "integrity": 94,
        "energy": 4389,
        "temp": 566
      },
      "fw_version": "v11.9"
    },
    {
      "id": "TER-FUS-017",
      "sector": "EARTH-CORE",
      "color": "blue",
      "service": "Fusion-Reactor",
      "status": "ACTIVE",
      "metrics": {
        "integrity": 100,
        "energy": 976,
        "temp": 614
      },
      "fw_version": "v11.1"
    },
    {
      "id": "TER-DEF-018",
      "sector": "EARTH-CORE",
      "color": "blue",
      "service": "Defense-Grid",
      "status": "ACTIVE",
      "metrics": {
        "integrity": 92,
        "energy": 3526,
        "temp": 544
      },
      "fw_version": "v11.4"
    },
    {
      "id": "TER-LIF-019",
      "sector": "EARTH-CORE",
      "color": "blue",
      "service": "Life-Support",
      "status": "ACTIVE",
      "metrics": {
        "integrity": 100,
        "energy": 4105,
        "temp": 875
      },
      "fw_version": "v11.4"
    },
    {
      "id": "LUN-QUA-000",
      "sector": "LUNAR-BASE",
      "color": "gray",
      "service": "Quantum-Net",
      "status": "ACTIVE",
      "metrics": {
        "integrity": 98,
        "energy": 3905,
        "temp": 421
      },
      "fw_version": "v10.9"
    },
    {
      "id": "LUN-AI--001",
      "sector": "LUNAR-BASE",
      "color": "gray",
      "service": "AI-Cortex",
      "status": "ACTIVE",
      "metrics": {
        "integrity": 93,
        "energy": 1977,
        "temp": 629
      },
      "fw_version": "v10.4"
    },
    {
      "id": "LUN-AI--002",
      "sector": "LUNAR-BASE",
      "color": "gray",
      "service": "AI-Cortex",
      "status": "ACTIVE",
      "metrics": {
        "integrity": 93,
        "energy": 1536,
        "temp": 415
      },
      "fw_version": "v10.2"
    },
    {
      "id": "LUN-DEF-003",
      "sector": "LUNAR-BASE",
      "color": "gray",
      "service": "Defense-Grid",
      "status": "ACTIVE",
      "metrics": {
        "integrity": 97,
        "energy": 1971,
        "temp": 830
      },
      "fw_version": "v12.4"
    },
    {
      "id": "LUN-AI--004",
      "sector": "LUNAR-BASE",
      "color": "gray",
      "service": "AI-Cortex",
      "status": "ACTIVE",
      "metrics": {
        "integrity": 99,
        "energy": 3701,
        "temp": 676
      },
      "fw_version": "v12.2"
    },
    {
      "id": "LUN-AI--005",
      "sector": "LUNAR-BASE",
      "color": "gray",
      "service": "AI-Cortex",
      "status": "ACTIVE",
      "metrics": {
        "integrity": 99,
        "energy": 486,
        "temp": 710
      },
      "fw_version": "v11.3"
    },
    {
      "id": "LUN-DEF-006",
      "sector": "LUNAR-BASE",
      "color": "gray",
      "service": "Defense-Grid",
      "status": "ACTIVE",
      "metrics": {
        "integrity": 98,
        "energy": 183,
        "temp": 368
      },
      "fw_version": "v12.0"
    },
    {
      "id": "LUN-DEF-007",
      "sector": "LUNAR-BASE",
      "color": "gray",
      "service": "Defense-Grid",
      "status": "ACTIVE",
      "metrics": {
        "integrity": 91,
        "energy": 1880,
        "temp": 413
      },
      "fw_version": "v10.0"
    },
    {
      "id": "LUN-QUA-008",
      "sector": "LUNAR-BASE",
      "color": "gray",
      "service": "Quantum-Net",
      "status": "ACTIVE",
      "metrics": {
        "integrity": 97,
        "energy": 1804,
        "temp": 440
      },
      "fw_version": "v11.6"
    },
    {
      "id": "LUN-DEF-009",
      "sector": "LUNAR-BASE",
      "color": "gray",
      "service": "Defense-Grid",
      "status": "ACTIVE",
      "metrics": {
        "integrity": 91,
        "energy": 3584,
        "temp": 286
      },
      "fw_version": "v12.0"
    },
    {
      "id": "LUN-DEF-010",
      "sector": "LUNAR-BASE",
      "color": "gray",
      "service": "Defense-Grid",
      "status": "ACTIVE",
      "metrics": {
        "integrity": 92,
        "energy": 1527,
        "temp": 362
      },
      "fw_version": "v12.2"
    },
    {
      "id": "LUN-FUS-011",
      "sector": "LUNAR-BASE",
      "color": "gray",
      "service": "Fusion-Reactor",
      "status": "ACTIVE",
      "metrics": {
        "integrity": 94,
        "energy": 4918,
        "temp": 711
      },
      "fw_version": "v11.0"
    },
    {
      "id": "LUN-QUA-012",
      "sector": "LUNAR-BASE",
      "color": "gray",
      "service": "Quantum-Net",
      "status": "ACTIVE",
      "metrics": {
        "integrity": 98,
        "energy": 1207,
        "temp": 155
      },
      "fw_version": "v11.3"
    },
    {
      "id": "LUN-FUS-013",
      "sector": "LUNAR-BASE",
      "color": "gray",
      "service": "Fusion-Reactor",
      "status": "ACTIVE",
      "metrics": {
        "integrity": 94,
        "energy": 953,
        "temp": 477
      },
      "fw_version": "v10.8"
    },
    {
      "id": "LUN-DEF-014",
      "sector": "LUNAR-BASE",
      "color": "gray",
      "service": "Defense-Grid",
      "status": "ACTIVE",
      "metrics": {
        "integrity": 93,
        "energy": 2459,
        "temp": 871
      },
      "fw_version": "v12.6"
    },
    {
      "id": "LUN-FUS-015",
      "sector": "LUNAR-BASE",
      "color": "gray",
      "service": "Fusion-Reactor",
      "status": "ACTIVE",
      "metrics": {
        "integrity": 94,
        "energy": 2248,
        "temp": 708
      },
      "fw_version": "v11.1"
    },
    {
      "id": "LUN-FUS-016",
      "sector": "LUNAR-BASE",
      "color": "gray",
      "service": "Fusion-Reactor",
      "status": "ACTIVE",
      "metrics": {
        "integrity": 100,
        "energy": 2553,
        "temp": 297
      },
      "fw_version": "v11.2"
    },
    {
      "id": "LUN-FUS-017",
      "sector": "LUNAR-BASE",
      "color": "gray",
      "service": "Fusion-Reactor",
      "status": "ACTIVE",
      "metrics": {
        "integrity": 100,
        "energy": 323,
        "temp": 474
      },
      "fw_version": "v12.6"
    },
    {
      "id": "LUN-AI--018",
      "sector": "LUNAR-BASE",
      "color": "gray",
      "service": "AI-Cortex",
      "status": "ACTIVE",
      "metrics": {
        "integrity": 91,
        "energy": 1758,
        "temp": 651
      },
      "fw_version": "v10.9"
    },
    {
      "id": "LUN-LIF-019",
      "sector": "LUNAR-BASE",
      "color": "gray",
      "service": "Life-Support",
      "status": "ACTIVE",
      "metrics": {
        "integrity": 91,
        "energy": 1477,
        "temp": 716
      },
      "fw_version": "v12.6"
    },
    {
      "id": "LUN-FUS-020",
      "sector": "LUNAR-BASE",
      "color": "gray",
      "service": "Fusion-Reactor",
      "status": "ACTIVE",
      "metrics": {
        "integrity": 92,
        "energy": 3940,
        "temp": 687
      },
      "fw_version": "v12.0"
    },
    {
      "id": "LUN-AI--021",
      "sector": "LUNAR-BASE",
      "color": "gray",
      "service": "AI-Cortex",
      "status": "ACTIVE",
      "metrics": {
        "integrity": 95,
        "energy": 3604,
        "temp": 871
      },
      "fw_version": "v12.7"
    },
    {
      "id": "LUN-AI--022",
      "sector": "LUNAR-BASE",
      "color": "gray",
      "service": "AI-Cortex",
      "status": "ACTIVE",
      "metrics": {
        "integrity": 92,
        "energy": 3636,
        "temp": 112
      },
      "fw_version": "v11.6"
    },
    {
      "id": "LUN-FUS-023",
      "sector": "LUNAR-BASE",
      "color": "gray",
      "service": "Fusion-Reactor",
      "status": "ACTIVE",
      "metrics": {
        "integrity": 99,
        "energy": 2929,
        "temp": 341
      },
      "fw_version": "v12.4"
    },
    {
      "id": "LUN-DEF-024",
      "sector": "LUNAR-BASE",
      "color": "gray",
      "service": "Defense-Grid",
      "status": "ACTIVE",
      "metrics": {
        "integrity": 97,
        "energy": 2876,
        "temp": 790
      },
      "fw_version": "v10.7"
    },
    {
      "id": "LUN-QUA-025",
      "sector": "LUNAR-BASE",
      "color": "gray",
      "service": "Quantum-Net",
      "status": "ACTIVE",
      "metrics": {
        "integrity": 92,
        "energy": 2224,
        "temp": 394
      },
      "fw_version": "v12.5"
    },
    {
      "id": "MRS-AI--000",
      "sector": "MARS-COLONY",
      "color": "red",
      "service": "AI-Cortex",
      "status": "ACTIVE",
      "metrics": {
        "integrity": 99,
        "energy": 3778,
        "temp": 725
      },
      "fw_version": "v12.3"
    },
    {
      "id": "MRS-FUS-001",
      "sector": "MARS-COLONY",
      "color": "red",
      "service": "Fusion-Reactor",
      "status": "ACTIVE",
      "metrics": {
        "integrity": 95,
        "energy": 2151,
        "temp": 836
      },
      "fw_version": "v12.7"
    },
    {
      "id": "MRS-DEF-002",
      "sector": "MARS-COLONY",
      "color": "red",
      "service": "Defense-Grid",
      "status": "ACTIVE",
      "metrics": {
        "integrity": 91,
        "energy": 2748,
        "temp": 896
      },
      "fw_version": "v11.2"
    },
    {
      "id": "MRS-FUS-003",
      "sector": "MARS-COLONY",
      "color": "red",
      "service": "Fusion-Reactor",
      "status": "ACTIVE",
      "metrics": {
        "integrity": 100,
        "energy": 1810,
        "temp": 336
      },
      "fw_version": "v10.9"
    },
    {
      "id": "MRS-FUS-004",
      "sector": "MARS-COLONY",
      "color": "red",
      "service": "Fusion-Reactor",
      "status": "ACTIVE",
      "metrics": {
        "integrity": 95,
        "energy": 4367,
        "temp": 370
      },
      "fw_version": "v11.4"
    },
    {
      "id": "MRS-AI--005",
      "sector": "MARS-COLONY",
      "color": "red",
      "service": "AI-Cortex",
      "status": "ACTIVE",
      "metrics": {
        "integrity": 97,
        "energy": 1578,
        "temp": 370
      },
      "fw_version": "v10.0"
    },
    {
      "id": "MRS-QUA-006",
      "sector": "MARS-COLONY",
      "color": "red",
      "service": "Quantum-Net",
      "status": "ACTIVE",
      "metrics": {
        "integrity": 90,
        "energy": 632,
        "temp": 101
      },
      "fw_version": "v10.1"
    },
    {
      "id": "MRS-DEF-007",
      "sector": "MARS-COLONY",
      "color": "red",
      "service": "Defense-Grid",
      "status": "ACTIVE",
      "metrics": {
        "integrity": 98,
        "energy": 4779,
        "temp": 794
      },
      "fw_version": "v11.7"
    },
    {
      "id": "MRS-DEF-008",
      "sector": "MARS-COLONY",
      "color": "red",
      "service": "Defense-Grid",
      "status": "ACTIVE",
      "metrics": {
        "integrity": 99,
        "energy": 3937,
        "temp": 329
      },
      "fw_version": "v11.4"
    },
    {
      "id": "MRS-LIF-009",
      "sector": "MARS-COLONY",
      "color": "red",
      "service": "Life-Support",
      "status": "ACTIVE",
      "metrics": {
        "integrity": 93,
        "energy": 3521,
        "temp": 837
      },
      "fw_version": "v10.5"
    },
    {
      "id": "MRS-FUS-010",
      "sector": "MARS-COLONY",
      "color": "red",
      "service": "Fusion-Reactor",
      "status": "ACTIVE",
      "metrics": {
        "integrity": 98,
        "energy": 4670,
        "temp": 371
      },
      "fw_version": "v12.5"
    },
    {
      "id": "MRS-FUS-011",
      "sector": "MARS-COLONY",
      "color": "red",
      "service": "Fusion-Reactor",
      "status": "ACTIVE",
      "metrics": {
        "integrity": 94,
        "energy": 3798,
        "temp": 877
      },
      "fw_version": "v10.1"
    },
    {
      "id": "MRS-FUS-012",
      "sector": "MARS-COLONY",
      "color": "red",
      "service": "Fusion-Reactor",
      "status": "ACTIVE",
      "metrics": {
        "integrity": 99,
        "energy": 2353,
        "temp": 726
      },
      "fw_version": "v10.6"
    },
    {
      "id": "MRS-LIF-013",
      "sector": "MARS-COLONY",
      "color": "red",
      "service": "Life-Support",
      "status": "ACTIVE",
      "metrics": {
        "integrity": 95,
        "energy": 3176,
        "temp": 213
      },
      "fw_version": "v11.6"
    },
    {
      "id": "MRS-AI--014",
      "sector": "MARS-COLONY",
      "color": "red",
      "service": "AI-Cortex",
      "status": "ACTIVE",
      "metrics": {
        "integrity": 95,
        "energy": 3199,
        "temp": 786
      },
      "fw_version": "v12.5"
    },
    {
      "id": "MRS-AI--015",
      "sector": "MARS-COLONY",
      "color": "red",
      "service": "AI-Cortex",
      "status": "ACTIVE",
      "metrics": {
        "integrity": 94,
        "energy": 2865,
        "temp": 251
      },
      "fw_version": "v10.3"
    },
    {
      "id": "MRS-LIF-016",
      "sector": "MARS-COLONY",
      "color": "red",
      "service": "Life-Support",
      "status": "ACTIVE",
      "metrics": {
        "integrity": 99,
        "energy": 1014,
        "temp": 374
      },
      "fw_version": "v12.4"
    },
    {
      "id": "MRS-DEF-017",
      "sector": "MARS-COLONY",
      "color": "red",
      "service": "Defense-Grid",
      "status": "ACTIVE",
      "metrics": {
        "integrity": 100,
        "energy": 3509,
        "temp": 795
      },
      "fw_version": "v10.8"
    },
    {
      "id": "MRS-QUA-018",
      "sector": "MARS-COLONY",
      "color": "red",
      "service": "Quantum-Net",
      "status": "ACTIVE",
      "metrics": {
        "integrity": 98,
        "energy": 4359,
        "temp": 198
      },
      "fw_version": "v11.4"
    },
    {
      "id": "MRS-AI--019",
      "sector": "MARS-COLONY",
      "color": "red",
      "service": "AI-Cortex",
      "status": "ACTIVE",
      "metrics": {
        "integrity": 98,
        "energy": 712,
        "temp": 795
      },
      "fw_version": "v11.0"
    },
    {
      "id": "MRS-LIF-020",
      "sector": "MARS-COLONY",
      "color": "red",
      "service": "Life-Support",
      "status": "ACTIVE",
      "metrics": {
        "integrity": 100,
        "energy": 4622,
        "temp": 676
      },
      "fw_version": "v10.7"
    },
    {
      "id": "TTN-DEF-000",
      "sector": "TITAN-OUTPOST",
      "color": "yellow",
      "service": "Defense-Grid",
      "status": "ACTIVE",
      "metrics": {
        "integrity": 95,
        "energy": 3526,
        "temp": 749
      },
      "fw_version": "v11.4"
    },
    {
      "id": "TTN-QUA-001",
      "sector": "TITAN-OUTPOST",
      "color": "yellow",
      "service": "Quantum-Net",
      "status": "ACTIVE",
      "metrics": {
        "integrity": 95,
        "energy": 3211,
        "temp": 175
      },
      "fw_version": "v11.0"
    },
    {
      "id": "TTN-DEF-002",
      "sector": "TITAN-OUTPOST",
      "color": "yellow",
      "service": "Defense-Grid",
      "status": "ACTIVE",
      "metrics": {
        "integrity": 92,
        "energy": 2517,
        "temp": 512
      },
      "fw_version": "v12.2"
    },
    {
      "id": "TTN-QUA-003",
      "sector": "TITAN-OUTPOST",
      "color": "yellow",
      "service": "Quantum-Net",
      "status": "ACTIVE",
      "metrics": {
        "integrity": 96,
        "energy": 3142,
        "temp": 376
      },
      "fw_version": "v11.7"
    },
    {
      "id": "TTN-FUS-004",
      "sector": "TITAN-OUTPOST",
      "color": "yellow",
      "service": "Fusion-Reactor",
      "status": "ACTIVE",
      "metrics": {
        "integrity": 98,
        "energy": 4801,
        "temp": 170
      },
      "fw_version": "v11.7"
    },
    {
      "id": "TTN-FUS-005",
      "sector": "TITAN-OUTPOST",
      "color": "yellow",
      "service": "Fusion-Reactor",
      "status": "ACTIVE",
      "metrics": {
        "integrity": 99,
        "energy": 3349,
        "temp": 342
      },
      "fw_version": "v11.5"
    },
    {
      "id": "TTN-FUS-006",
      "sector": "TITAN-OUTPOST",
      "color": "yellow",
      "service": "Fusion-Reactor",
      "status": "ACTIVE",
      "metrics": {
        "integrity": 92,
        "energy": 2937,
        "temp": 264
      },
      "fw_version": "v10.1"
    },
    {
      "id": "TTN-LIF-007",
      "sector": "TITAN-OUTPOST",
      "color": "yellow",
      "service": "Life-Support",
      "status": "ACTIVE",
      "metrics": {
        "integrity": 93,
        "energy": 1847,
        "temp": 673
      },
      "fw_version": "v12.7"
    },
    {
      "id": "TTN-FUS-008",
      "sector": "TITAN-OUTPOST",
      "color": "yellow",
      "service": "Fusion-Reactor",
      "status": "ACTIVE",
      "metrics": {
        "integrity": 94,
        "energy": 486,
        "temp": 403
      },
      "fw_version": "v11.7"
    },
    {
      "id": "TTN-AI--009",
      "sector": "TITAN-OUTPOST",
      "color": "yellow",
      "service": "AI-Cortex",
      "status": "ACTIVE",
      "metrics": {
        "integrity": 92,
        "energy": 1841,
        "temp": 174
      },
      "fw_version": "v10.5"
    },
    {
      "id": "TTN-QUA-010",
      "sector": "TITAN-OUTPOST",
      "color": "yellow",
      "service": "Quantum-Net",
      "status": "ACTIVE",
      "metrics": {
        "integrity": 92,
        "energy": 2715,
        "temp": 251
      },
      "fw_version": "v11.1"
    },
    {
      "id": "TTN-QUA-011",
      "sector": "TITAN-OUTPOST",
      "color": "yellow",
      "service": "Quantum-Net",
      "status": "ACTIVE",
      "metrics": {
        "integrity": 94,
        "energy": 375,
        "temp": 284
      },
      "fw_version": "v12.2"
    },
    {
      "id": "TTN-QUA-012",
      "sector": "TITAN-OUTPOST",
      "color": "yellow",
      "service": "Quantum-Net",
      "status": "ACTIVE",
      "metrics": {
        "integrity": 94,
        "energy": 239,
        "temp": 230
      },
      "fw_version": "v11.0"
    },
    {
      "id": "TTN-AI--013",
      "sector": "TITAN-OUTPOST",
      "color": "yellow",
      "service": "AI-Cortex",
      "status": "ACTIVE",
      "metrics": {
        "integrity": 96,
        "energy": 3781,
        "temp": 717
      },
      "fw_version": "v12.7"
    },
    {
      "id": "TTN-QUA-014",
      "sector": "TITAN-OUTPOST",
      "color": "yellow",
      "service": "Quantum-Net",
      "status": "ACTIVE",
      "metrics": {
        "integrity": 98,
        "energy": 3756,
        "temp": 129
      },
      "fw_version": "v11.1"
    },
    {
      "id": "TTN-DEF-015",
      "sector": "TITAN-OUTPOST",
      "color": "yellow",
      "service": "Defense-Grid",
      "status": "ACTIVE",
      "metrics": {
        "integrity": 100,
        "energy": 3216,
        "temp": 880
      },
      "fw_version": "v12.5"
    },
    {
      "id": "TTN-FUS-016",
      "sector": "TITAN-OUTPOST",
      "color": "yellow",
      "service": "Fusion-Reactor",
      "status": "ACTIVE",
      "metrics": {
        "integrity": 100,
        "energy": 851,
        "temp": 331
      },
      "fw_version": "v11.3"
    },
    {
      "id": "TTN-FUS-017",
      "sector": "TITAN-OUTPOST",
      "color": "yellow",
      "service": "Fusion-Reactor",
      "status": "ACTIVE",
      "metrics": {
        "integrity": 100,
        "energy": 4797,
        "temp": 274
      },
      "fw_version": "v10.8"
    },
    {
      "id": "TTN-FUS-018",
      "sector": "TITAN-OUTPOST",
      "color": "yellow",
      "service": "Fusion-Reactor",
      "status": "ACTIVE",
      "metrics": {
        "integrity": 99,
        "energy": 2610,
        "temp": 462
      },
      "fw_version": "v11.4"
    },
    {
      "id": "TTN-AI--019",
      "sector": "TITAN-OUTPOST",
      "color": "yellow",
      "service": "AI-Cortex",
      "status": "ACTIVE",
      "metrics": {
        "integrity": 90,
        "energy": 625,
        "temp": 308
      },
      "fw_version": "v11.5"
    },
    {
      "id": "TTN-FUS-020",
      "sector": "TITAN-OUTPOST",
      "color": "yellow",
      "service": "Fusion-Reactor",
      "status": "ACTIVE",
      "metrics": {
        "integrity": 100,
        "energy": 3587,
        "temp": 556
      },
      "fw_version": "v11.1"
    },
    {
      "id": "TTN-DEF-021",
      "sector": "TITAN-OUTPOST",
      "color": "yellow",
      "service": "Defense-Grid",
      "status": "ACTIVE",
      "metrics": {
        "integrity": 94,
        "energy": 714,
        "temp": 605
      },
      "fw_version": "v12.9"
    },
    {
      "id": "TTN-LIF-022",
      "sector": "TITAN-OUTPOST",
      "color": "yellow",
      "service": "Life-Support",
      "status": "ACTIVE",
      "metrics": {
        "integrity": 95,
        "energy": 2351,
        "temp": 508
      },
      "fw_version": "v10.1"
    },
    {
      "id": "TTN-DEF-023",
      "sector": "TITAN-OUTPOST",
      "color": "yellow",
      "service": "Defense-Grid",
      "status": "ACTIVE",
      "metrics": {
        "integrity": 92,
        "energy": 4595,
        "temp": 693
      },
      "fw_version": "v10.6"
    },
    {
      "id": "ORB-FUS-000",
      "sector": "ORBITAL-STATION",
      "color": "cyan",
      "service": "Fusion-Reactor",
      "status": "ACTIVE",
      "metrics": {
        "integrity": 93,
        "energy": 4649,
        "temp": 741
      },
      "fw_version": "v11.8"
    },
    {
      "id": "ORB-AI--001",
      "sector": "ORBITAL-STATION",
      "color": "cyan",
      "service": "AI-Cortex",
      "status": "ACTIVE",
      "metrics": {
        "integrity": 98,
        "energy": 4929,
        "temp": 319
      },
      "fw_version": "v10.1"
    },
    {
      "id": "ORB-FUS-002",
      "sector": "ORBITAL-STATION",
      "color": "cyan",
      "service": "Fusion-Reactor",
      "status": "ACTIVE",
      "metrics": {
        "integrity": 92,
        "energy": 760,
        "temp": 358
      },
      "fw_version": "v12.8"
    },
    {
      "id": "ORB-FUS-003",
      "sector": "ORBITAL-STATION",
      "color": "cyan",
      "service": "Fusion-Reactor",
      "status": "ACTIVE",
      "metrics": {
        "integrity": 97,
        "energy": 3095,
        "temp": 294
      },
      "fw_version": "v11.2"
    },
    {
      "id": "ORB-AI--004",
      "sector": "ORBITAL-STATION",
      "color": "cyan",
      "service": "AI-Cortex",
      "status": "ACTIVE",
      "metrics": {
        "integrity": 97,
        "energy": 4633,
        "temp": 770
      },
      "fw_version": "v10.4"
    },
    {
      "id": "ORB-DEF-005",
      "sector": "ORBITAL-STATION",
      "color": "cyan",
      "service": "Defense-Grid",
      "status": "ACTIVE",
      "metrics": {
        "integrity": 98,
        "energy": 3326,
        "temp": 222
      },
      "fw_version": "v10.3"
    },
    {
      "id": "ORB-AI--006",
      "sector": "ORBITAL-STATION",
      "color": "cyan",
      "service": "AI-Cortex",
      "status": "ACTIVE",
      "metrics": {
        "integrity": 97,
        "energy": 4054,
        "temp": 193
      },
      "fw_version": "v12.1"
    },
    {
      "id": "ORB-QUA-007",
      "sector": "ORBITAL-STATION",
      "color": "cyan",
      "service": "Quantum-Net",
      "status": "ACTIVE",
      "metrics": {
        "integrity": 92,
        "energy": 1122,
        "temp": 500
      },
      "fw_version": "v11.3"
    },
    {
      "id": "ORB-FUS-008",
      "sector": "ORBITAL-STATION",
      "color": "cyan",
      "service": "Fusion-Reactor",
      "status": "ACTIVE",
      "metrics": {
        "integrity": 92,
        "energy": 3332,
        "temp": 188
      },
      "fw_version": "v10.5"
    },
    {
      "id": "ORB-LIF-009",
      "sector": "ORBITAL-STATION",
      "color": "cyan",
      "service": "Life-Support",
      "status": "ACTIVE",
      "metrics": {
        "integrity": 98,
        "energy": 2281,
        "temp": 397
      },
      "fw_version": "v11.9"
    },
    {
      "id": "ORB-DEF-010",
      "sector": "ORBITAL-STATION",
      "color": "cyan",
      "service": "Defense-Grid",
      "status": "ACTIVE",
      "metrics": {
        "integrity": 99,
        "energy": 2531,
        "temp": 448
      },
      "fw_version": "v11.9"
    },
    {
      "id": "ORB-FUS-011",
      "sector": "ORBITAL-STATION",
      "color": "cyan",
      "service": "Fusion-Reactor",
      "status": "ACTIVE",
      "metrics": {
        "integrity": 97,
        "energy": 3635,
        "temp": 635
      },
      "fw_version": "v12.6"
    },
    {
      "id": "ORB-LIF-012",
      "sector": "ORBITAL-STATION",
      "color": "cyan",
      "service": "Life-Support",
      "status": "ACTIVE",
      "metrics": {
        "integrity": 98,
        "energy": 4221,
        "temp": 323
      },
      "fw_version": "v11.8"
    },
    {
      "id": "ORB-FUS-013",
      "sector": "ORBITAL-STATION",
      "color": "cyan",
      "service": "Fusion-Reactor",
      "status": "ACTIVE",
      "metrics": {
        "integrity": 99,
        "energy": 967,
        "temp": 778
      },
      "fw_version": "v12.3"
    },
    {
      "id": "ORB-AI--014",
      "sector": "ORBITAL-STATION",
      "color": "cyan",
      "service": "AI-Cortex",
      "status": "ACTIVE",
      "metrics": {
        "integrity": 94,
        "energy": 3681,
        "temp": 649
      },
      "fw_version": "v11.1"
    },
    {
      "id": "ORB-FUS-015",
      "sector": "ORBITAL-STATION",
      "color": "cyan",
      "service": "Fusion-Reactor",
      "status": "ACTIVE",
      "metrics": {
        "integrity": 96,
        "energy": 1203,
        "temp": 713
      },
      "fw_version": "v10.6"
    },
    {
      "id": "ORB-AI--016",
      "sector": "ORBITAL-STATION",
      "color": "cyan",
      "service": "AI-Cortex",
      "status": "ACTIVE",
      "metrics": {
        "integrity": 90,
        "energy": 4615,
        "temp": 161
      },
      "fw_version": "v12.3"
    },
    {
      "id": "ORB-AI--017",
      "sector": "ORBITAL-STATION",
      "color": "cyan",
      "service": "AI-Cortex",
      "status": "ACTIVE",
      "metrics": {
        "integrity": 100,
        "energy": 4150,
        "temp": 113
      },
      "fw_version": "v11.7"
    },
    {
      "id": "ORB-FUS-018",
      "sector": "ORBITAL-STATION",
      "color": "cyan",
      "service": "Fusion-Reactor",
      "status": "ACTIVE",
      "metrics": {
        "integrity": 93,
        "energy": 4535,
        "temp": 854
      },
      "fw_version": "v10.2"
    },
    {
      "id": "ORB-LIF-019",
      "sector": "ORBITAL-STATION",
      "color": "cyan",
      "service": "Life-Support",
      "status": "ACTIVE",
      "metrics": {
        "integrity": 90,
        "energy": 1797,
        "temp": 175
      },
      "fw_version": "v11.2"
    },
    {
      "id": "ORB-QUA-020",
      "sector": "ORBITAL-STATION",
      "color": "cyan",
      "service": "Quantum-Net",
      "status": "ACTIVE",
      "metrics": {
        "integrity": 91,
        "energy": 2240,
        "temp": 824
      },
      "fw_version": "v12.0"
    },
    {
      "id": "ORB-AI--021",
      "sector": "ORBITAL-STATION",
      "color": "cyan",
      "service": "AI-Cortex",
      "status": "ACTIVE",
      "metrics": {
        "integrity": 94,
        "energy": 4291,
        "temp": 310
      },
      "fw_version": "v10.5"
    },
    {
      "id": "ORB-FUS-022",
      "sector": "ORBITAL-STATION",
      "color": "cyan",
      "service": "Fusion-Reactor",
      "status": "ACTIVE",
      "metrics": {
        "integrity": 97,
        "energy": 465,
        "temp": 725
      },
      "fw_version": "v10.6"
    },
    {
      "id": "ORB-QUA-023",
      "sector": "ORBITAL-STATION",
      "color": "cyan",
      "service": "Quantum-Net",
      "status": "ACTIVE",
      "metrics": {
        "integrity": 95,
        "energy": 2680,
        "temp": 513
      },
      "fw_version": "v11.7"
    },
    {
      "id": "ORB-DEF-024",
      "sector": "ORBITAL-STATION",
      "color": "cyan",
      "service": "Defense-Grid",
      "status": "ACTIVE",
      "metrics": {
        "integrity": 98,
        "energy": 3835,
        "temp": 439
      },
      "fw_version": "v11.6"
    }
  ],
  "global_integrity": 94
}