{
  "generated_at": "2025-12-31T09:13:09.207059",
  "radar": [
    {
      "angle": 137,
      "dist": 41,
      "type": "FRIENDLY"
    },
    {
      "angle": 287,
      "dist": 30,
      "type": "UNKNOWN"
    },
    {
      "angle": 225,
      "dist": 30,
      "type": "FRIENDLY"
    },
    {
      "angle": 102,
      "dist": 74,
      "type": "HOSTILE"
    },
    {
      "angle": 270,
      "dist": 15,
      "type": "FRIENDLY"
    }
  ],
  "logs": [
    "[09:13:09] main/tags process_id=6335 status=SYNC",
    "[09:13:09] posts/app/list process_id=7862 status=SYNC",
    "[09:13:09] tags/category process_id=9653 status=SYNC",
    "[09:13:09] tag process_id=3686 status=SYNC",
    "[09:13:09] search/tag/search process_id=1113 status=SYNC",
    "[09:13:09] category process_id=5383 status=SYNC",
    "[09:13:09] main/categories/search process_id=7421 status=SYNC",
    "[09:13:09] search/category process_id=4510 status=SYNC",
    "[09:13:09] app process_id=5891 status=SYNC",
    "[09:13:09] explore/tag/category process_id=4309 status=SYNC",
    "[09:13:09] tag/tags/category process_id=2771 status=SYNC",
    "[09:13:09] main/main/main process_id=7369 status=SYNC",
    "[09:13:09] blog/blog process_id=8391 status=SYNC",
    "[09:13:09] wp-content/category/main process_id=6984 status=SYNC",
    "[09:13:09] blog/posts/categories process_id=4550 status=SYNC",
    "[09:13:09] category/tag/list process_id=9840 status=SYNC",
    "[09:13:09] blog process_id=8804 status=SYNC",
    "[09:13:09] list/search/wp-content process_id=9780 status=SYNC",
    "[09:13:09] wp-content/tag/categories process_id=8456 status=SYNC",
    "[09:13:09] wp-content/explore/explore process_id=9420 status=SYNC"
  ],
  "nodes": [
    {
      "id": "TER-DEF-000",
      "sector": "EARTH-CORE",
      "color": "blue",
      "service": "Defense-Grid",
      "status": "ACTIVE",
      "metrics": {
        "integrity": 99,
        "energy": 323,
        "temp": 300
      },
      "fw_version": "v10.9"
    },
    {
      "id": "TER-DEF-001",
      "sector": "EARTH-CORE",
      "color": "blue",
      "service": "Defense-Grid",
      "status": "ACTIVE",
      "metrics": {
        "integrity": 93,
        "energy": 2236,
        "temp": 443
      },
      "fw_version": "v10.0"
    },
    {
      "id": "TER-DEF-002",
      "sector": "EARTH-CORE",
      "color": "blue",
      "service": "Defense-Grid",
      "status": "ACTIVE",
      "metrics": {
        "integrity": 100,
        "energy": 1303,
        "temp": 202
      },
      "fw_version": "v11.1"
    },
    {
      "id": "TER-DEF-003",
      "sector": "EARTH-CORE",
      "color": "blue",
      "service": "Defense-Grid",
      "status": "ACTIVE",
      "metrics": {
        "integrity": 97,
        "energy": 3150,
        "temp": 379
      },
      "fw_version": "v12.5"
    },
    {
      "id": "TER-LIF-004",
      "sector": "EARTH-CORE",
      "color": "blue",
      "service": "Life-Support",
      "status": "CRITICAL",
      "metrics": {
        "integrity": 68,
        "energy": 1495,
        "temp": 761
      },
      "fw_version": "v10.1"
    },
    {
      "id": "TER-QUA-005",
      "sector": "EARTH-CORE",
      "color": "blue",
      "service": "Quantum-Net",
      "status": "ACTIVE",
      "metrics": {
        "integrity": 96,
        "energy": 1958,
        "temp": 703
      },
      "fw_version": "v10.6"
    },
    {
      "id": "TER-LIF-006",
      "sector": "EARTH-CORE",
      "color": "blue",
      "service": "Life-Support",
      "status": "ACTIVE",
      "metrics": {
        "integrity": 97,
        "energy": 2975,
        "temp": 213
      },
      "fw_version": "v10.9"
    },
    {
      "id": "TER-FUS-007",
      "sector": "EARTH-CORE",
      "color": "blue",
      "service": "Fusion-Reactor",
      "status": "ACTIVE",
      "metrics": {
        "integrity": 98,
        "energy": 2008,
        "temp": 884
      },
      "fw_version": "v12.5"
    },
    {
      "id": "TER-DEF-008",
      "sector": "EARTH-CORE",
      "color": "blue",
      "service": "Defense-Grid",
      "status": "ACTIVE",
      "metrics": {
        "integrity": 92,
        "energy": 623,
        "temp": 773
      },
      "fw_version": "v10.1"
    },
    {
      "id": "TER-AI--009",
      "sector": "EARTH-CORE",
      "color": "blue",
      "service": "AI-Cortex",
      "status": "ACTIVE",
      "metrics": {
        "integrity": 94,
        "energy": 1481,
        "temp": 676
      },
      "fw_version": "v12.7"
    },
    {
      "id": "TER-FUS-010",
      "sector": "EARTH-CORE",
      "color": "blue",
      "service": "Fusion-Reactor",
      "status": "ACTIVE",
      "metrics": {
        "integrity": 98,
        "energy": 474,
        "temp": 162
      },
      "fw_version": "v11.3"
    },
    {
      "id": "TER-LIF-011",
      "sector": "EARTH-CORE",
      "color": "blue",
      "service": "Life-Support",
      "status": "ACTIVE",
      "metrics": {
        "integrity": 90,
        "energy": 2300,
        "temp": 704
      },
      "fw_version": "v12.6"
    },
    {
      "id": "TER-LIF-012",
      "sector": "EARTH-CORE",
      "color": "blue",
      "service": "Life-Support",
      "status": "ACTIVE",
      "metrics": {
        "integrity": 94,
        "energy": 2895,
        "temp": 639
      },
      "fw_version": "v12.1"
    },
    {
      "id": "TER-AI--013",
      "sector": "EARTH-CORE",
      "color": "blue",
      "service": "AI-Cortex",
      "status": "ACTIVE",
      "metrics": {
        "integrity": 100,
        "energy": 4302,
        "temp": 459
      },
      "fw_version": "v10.0"
    },
    {
      "id": "TER-DEF-014",
      "sector": "EARTH-CORE",
      "color": "blue",
      "service": "Defense-Grid",
      "status": "ACTIVE",
      "metrics": {
        "integrity": 100,
        "energy": 3551,
        "temp": 578
      },
      "fw_version": "v12.2"
    },
    {
      "id": "TER-QUA-015",
      "sector": "EARTH-CORE",
      "color": "blue",
      "service": "Quantum-Net",
      "status": "ACTIVE",
      "metrics": {
        "integrity": 99,
        "energy": 3201,
        "temp": 817
      },
      "fw_version": "v11.0"
    },
    {
      "id": "TER-FUS-016",
      "sector": "EARTH-CORE",
      "color": "blue",
      "service": "Fusion-Reactor",
      "status": "ACTIVE",
      "metrics": {
        "integrity": 94,
        "energy": 460,
        "temp": 486
      },
      "fw_version": "v12.0"
    },
    {
      "id": "TER-AI--017",
      "sector": "EARTH-CORE",
      "color": "blue",
      "service": "AI-Cortex",
      "status": "ACTIVE",
      "metrics": {
        "integrity": 90,
        "energy": 3196,
        "temp": 582
      },
      "fw_version": "v10.5"
    },
    {
      "id": "TER-FUS-018",
      "sector": "EARTH-CORE",
      "color": "blue",
      "service": "Fusion-Reactor",
      "status": "CRITICAL",
      "metrics": {
        "integrity": 73,
        "energy": 867,
        "temp": 709
      },
      "fw_version": "v12.7"
    },
    {
      "id": "TER-QUA-019",
      "sector": "EARTH-CORE",
      "color": "blue",
      "service": "Quantum-Net",
      "status": "ACTIVE",
      "metrics": {
        "integrity": 100,
        "energy": 3340,
        "temp": 541
      },
      "fw_version": "v11.1"
    },
    {
      "id": "TER-AI--020",
      "sector": "EARTH-CORE",
      "color": "blue",
      "service": "AI-Cortex",
      "status": "ACTIVE",
      "metrics": {
        "integrity": 100,
        "energy": 2804,
        "temp": 763
      },
      "fw_version": "v11.6"
    },
    {
      "id": "TER-LIF-021",
      "sector": "EARTH-CORE",
      "color": "blue",
      "service": "Life-Support",
      "status": "ACTIVE",
      "metrics": {
        "integrity": 93,
        "energy": 3211,
        "temp": 675
      },
      "fw_version": "v10.4"
    },
    {
      "id": "LUN-DEF-000",
      "sector": "LUNAR-BASE",
      "color": "gray",
      "service": "Defense-Grid",
      "status": "ACTIVE",
      "metrics": {
        "integrity": 97,
        "energy": 3150,
        "temp": 685
      },
      "fw_version": "v12.7"
    },
    {
      "id": "LUN-QUA-001",
      "sector": "LUNAR-BASE",
      "color": "gray",
      "service": "Quantum-Net",
      "status": "ACTIVE",
      "metrics": {
        "integrity": 99,
        "energy": 3645,
        "temp": 179
      },
      "fw_version": "v12.5"
    },
    {
      "id": "LUN-AI--002",
      "sector": "LUNAR-BASE",
      "color": "gray",
      "service": "AI-Cortex",
      "status": "ACTIVE",
      "metrics": {
        "integrity": 96,
        "energy": 244,
        "temp": 446
      },
      "fw_version": "v11.6"
    },
    {
      "id": "LUN-DEF-003",
      "sector": "LUNAR-BASE",
      "color": "gray",
      "service": "Defense-Grid",
      "status": "ACTIVE",
      "metrics": {
        "integrity": 95,
        "energy": 3170,
        "temp": 581
      },
      "fw_version": "v10.4"
    },
    {
      "id": "LUN-DEF-004",
      "sector": "LUNAR-BASE",
      "color": "gray",
      "service": "Defense-Grid",
      "status": "ACTIVE",
      "metrics": {
        "integrity": 98,
        "energy": 4282,
        "temp": 673
      },
      "fw_version": "v10.4"
    },
    {
      "id": "LUN-QUA-005",
      "sector": "LUNAR-BASE",
      "color": "gray",
      "service": "Quantum-Net",
      "status": "ACTIVE",
      "metrics": {
        "integrity": 93,
        "energy": 2895,
        "temp": 818
      },
      "fw_version": "v12.6"
    },
    {
      "id": "LUN-DEF-006",
      "sector": "LUNAR-BASE",
      "color": "gray",
      "service": "Defense-Grid",
      "status": "ACTIVE",
      "metrics": {
        "integrity": 99,
        "energy": 1765,
        "temp": 337
      },
      "fw_version": "v10.2"
    },
    {
      "id": "LUN-AI--007",
      "sector": "LUNAR-BASE",
      "color": "gray",
      "service": "AI-Cortex",
      "status": "ACTIVE",
      "metrics": {
        "integrity": 99,
        "energy": 4705,
        "temp": 117
      },
      "fw_version": "v10.8"
    },
    {
      "id": "LUN-FUS-008",
      "sector": "LUNAR-BASE",
      "color": "gray",
      "service": "Fusion-Reactor",
      "status": "ACTIVE",
      "metrics": {
        "integrity": 91,
        "energy": 1796,
        "temp": 500
      },
      "fw_version": "v11.4"
    },
    {
      "id": "LUN-QUA-009",
      "sector": "LUNAR-BASE",
      "color": "gray",
      "service": "Quantum-Net",
      "status": "ACTIVE",
      "metrics": {
        "integrity": 95,
        "energy": 3149,
        "temp": 747
      },
      "fw_version": "v12.4"
    },
    {
      "id": "LUN-DEF-010",
      "sector": "LUNAR-BASE",
      "color": "gray",
      "service": "Defense-Grid",
      "status": "ACTIVE",
      "metrics": {
        "integrity": 93,
        "energy": 2980,
        "temp": 712
      },
      "fw_version": "v12.7"
    },
    {
      "id": "LUN-FUS-011",
      "sector": "LUNAR-BASE",
      "color": "gray",
      "service": "Fusion-Reactor",
      "status": "ACTIVE",
      "metrics": {
        "integrity": 92,
        "energy": 3201,
        "temp": 610
      },
      "fw_version": "v11.9"
    },
    {
      "id": "LUN-FUS-012",
      "sector": "LUNAR-BASE",
      "color": "gray",
      "service": "Fusion-Reactor",
      "status": "ACTIVE",
      "metrics": {
        "integrity": 92,
        "energy": 1413,
        "temp": 873
      },
      "fw_version": "v10.8"
    },
    {
      "id": "LUN-LIF-013",
      "sector": "LUNAR-BASE",
      "color": "gray",
      "service": "Life-Support",
      "status": "ACTIVE",
      "metrics": {
        "integrity": 92,
        "energy": 2527,
        "temp": 686
      },
      "fw_version": "v10.0"
    },
    {
      "id": "LUN-AI--014",
      "sector": "LUNAR-BASE",
      "color": "gray",
      "service": "AI-Cortex",
      "status": "ACTIVE",
      "metrics": {
        "integrity": 91,
        "energy": 4397,
        "temp": 878
      },
      "fw_version": "v10.3"
    },
    {
      "id": "LUN-FUS-015",
      "sector": "LUNAR-BASE",
      "color": "gray",
      "service": "Fusion-Reactor",
      "status": "ACTIVE",
      "metrics": {
        "integrity": 92,
        "energy": 1130,
        "temp": 138
      },
      "fw_version": "v11.3"
    },
    {
      "id": "LUN-FUS-016",
      "sector": "LUNAR-BASE",
      "color": "gray",
      "service": "Fusion-Reactor",
      "status": "ACTIVE",
      "metrics": {
        "integrity": 93,
        "energy": 1454,
        "temp": 322
      },
      "fw_version": "v10.7"
    },
    {
      "id": "LUN-AI--017",
      "sector": "LUNAR-BASE",
      "color": "gray",
      "service": "AI-Cortex",
      "status": "ACTIVE",
      "metrics": {
        "integrity": 100,
        "energy": 3006,
        "temp": 370
      },
      "fw_version": "v12.6"
    },
    {
      "id": "LUN-QUA-018",
      "sector": "LUNAR-BASE",
      "color": "gray",
      "service": "Quantum-Net",
      "status": "ACTIVE",
      "metrics": {
        "integrity": 98,
        "energy": 726,
        "temp": 142
      },
      "fw_version": "v10.4"
    },
    {
      "id": "LUN-FUS-019",
      "sector": "LUNAR-BASE",
      "color": "gray",
      "service": "Fusion-Reactor",
      "status": "ACTIVE",
      "metrics": {
        "integrity": 93,
        "energy": 2440,
        "temp": 657
      },
      "fw_version": "v11.9"
    },
    {
      "id": "LUN-FUS-020",
      "sector": "LUNAR-BASE",
      "color": "gray",
      "service": "Fusion-Reactor",
      "status": "ACTIVE",
      "metrics": {
        "integrity": 95,
        "energy": 2929,
        "temp": 554
      },
      "fw_version": "v10.1"
    },
    {
      "id": "LUN-DEF-021",
      "sector": "LUNAR-BASE",
      "color": "gray",
      "service": "Defense-Grid",
      "status": "ACTIVE",
      "metrics": {
        "integrity": 99,
        "energy": 1254,
        "temp": 144
      },
      "fw_version": "v10.1"
    },
    {
      "id": "LUN-FUS-022",
      "sector": "LUNAR-BASE",
      "color": "gray",
      "service": "Fusion-Reactor",
      "status": "ACTIVE",
      "metrics": {
        "integrity": 99,
        "energy": 3248,
        "temp": 739
      },
      "fw_version": "v11.8"
    },
    {
      "id": "LUN-LIF-023",
      "sector": "LUNAR-BASE",
      "color": "gray",
      "service": "Life-Support",
      "status": "ACTIVE",
      "metrics": {
        "integrity": 99,
        "energy": 1369,
        "temp": 527
      },
      "fw_version": "v10.9"
    },
    {
      "id": "LUN-DEF-024",
      "sector": "LUNAR-BASE",
      "color": "gray",
      "service": "Defense-Grid",
      "status": "ACTIVE",
      "metrics": {
        "integrity": 93,
        "energy": 3638,
        "temp": 836
      },
      "fw_version": "v10.0"
    },
    {
      "id": "LUN-FUS-025",
      "sector": "LUNAR-BASE",
      "color": "gray",
      "service": "Fusion-Reactor",
      "status": "ACTIVE",
      "metrics": {
        "integrity": 96,
        "energy": 2871,
        "temp": 893
      },
      "fw_version": "v10.0"
    },
    {
      "id": "MRS-QUA-000",
      "sector": "MARS-COLONY",
      "color": "red",
      "service": "Quantum-Net",
      "status": "ACTIVE",
      "metrics": {
        "integrity": 98,
        "energy": 897,
        "temp": 712
      },
      "fw_version": "v12.2"
    },
    {
      "id": "MRS-AI--001",
      "sector": "MARS-COLONY",
      "color": "red",
      "service": "AI-Cortex",
      "status": "ACTIVE",
      "metrics": {
        "integrity": 93,
        "energy": 736,
        "temp": 863
      },
      "fw_version": "v12.6"
    },
    {
      "id": "MRS-LIF-002",
      "sector": "MARS-COLONY",
      "color": "red",
      "service": "Life-Support",
      "status": "ACTIVE",
      "metrics": {
        "integrity": 94,
        "energy": 2715,
        "temp": 878
      },
      "fw_version": "v10.9"
    },
    {
      "id": "MRS-LIF-003",
      "sector": "MARS-COLONY",
      "color": "red",
      "service": "Life-Support",
      "status": "CRITICAL",
      "metrics": {
        "integrity": 74,
        "energy": 3286,
        "temp": 349
      },
      "fw_version": "v12.0"
    },
    {
      "id": "MRS-FUS-004",
      "sector": "MARS-COLONY",
      "color": "red",
      "service": "Fusion-Reactor",
      "status": "ACTIVE",
      "metrics": {
        "integrity": 91,
        "energy": 2079,
        "temp": 625
      },
      "fw_version": "v12.0"
    },
    {
      "id": "MRS-DEF-005",
      "sector": "MARS-COLONY",
      "color": "red",
      "service": "Defense-Grid",
      "status": "ACTIVE",
      "metrics": {
        "integrity": 97,
        "energy": 4697,
        "temp": 443
      },
      "fw_version": "v11.0"
    },
    {
      "id": "MRS-QUA-006",
      "sector": "MARS-COLONY",
      "color": "red",
      "service": "Quantum-Net",
      "status": "ACTIVE",
      "metrics": {
        "integrity": 100,
        "energy": 2700,
        "temp": 373
      },
      "fw_version": "v10.4"
    },
    {
      "id": "MRS-FUS-007",
      "sector": "MARS-COLONY",
      "color": "red",
      "service": "Fusion-Reactor",
      "status": "ACTIVE",
      "metrics": {
        "integrity": 96,
        "energy": 1730,
        "temp": 799
      },
      "fw_version": "v11.1"
    },
    {
      "id": "MRS-FUS-008",
      "sector": "MARS-COLONY",
      "color": "red",
      "service": "Fusion-Reactor",
      "status": "ACTIVE",
      "metrics": {
        "integrity": 90,
        "energy": 4839,
        "temp": 256
      },
      "fw_version": "v11.5"
    },
    {
      "id": "MRS-LIF-009",
      "sector": "MARS-COLONY",
      "color": "red",
      "service": "Life-Support",
      "status": "ACTIVE",
      "metrics": {
        "integrity": 92,
        "energy": 874,
        "temp": 495
      },
      "fw_version": "v10.8"
    },
    {
      "id": "MRS-QUA-010",
      "sector": "MARS-COLONY",
      "color": "red",
      "service": "Quantum-Net",
      "status": "ACTIVE",
      "metrics": {
        "integrity": 94,
        "energy": 1839,
        "temp": 847
      },
      "fw_version": "v11.0"
    },
    {
      "id": "MRS-LIF-011",
      "sector": "MARS-COLONY",
      "color": "red",
      "service": "Life-Support",
      "status": "ACTIVE",
      "metrics": {
        "integrity": 94,
        "energy": 1059,
        "temp": 820
      },
      "fw_version": "v10.9"
    },
    {
      "id": "MRS-DEF-012",
      "sector": "MARS-COLONY",
      "color": "red",
      "service": "Defense-Grid",
      "status": "ACTIVE",
      "metrics": {
        "integrity": 95,
        "energy": 3017,
        "temp": 202
      },
      "fw_version": "v12.6"
    },
    {
      "id": "MRS-QUA-013",
      "sector": "MARS-COLONY",
      "color": "red",
      "service": "Quantum-Net",
      "status": "ACTIVE",
      "metrics": {
        "integrity": 97,
        "energy": 4508,
        "temp": 519
      },
      "fw_version": "v12.2"
    },
    {
      "id": "MRS-FUS-014",
      "sector": "MARS-COLONY",
      "color": "red",
      "service": "Fusion-Reactor",
      "status": "ACTIVE",
      "metrics": {
        "integrity": 93,
        "energy": 1864,
        "temp": 421
      },
      "fw_version": "v12.7"
    },
    {
      "id": "MRS-AI--015",
      "sector": "MARS-COLONY",
      "color": "red",
      "service": "AI-Cortex",
      "status": "ACTIVE",
      "metrics": {
        "integrity": 91,
        "energy": 2983,
        "temp": 787
      },
      "fw_version": "v12.0"
    },
    {
      "id": "MRS-LIF-016",
      "sector": "MARS-COLONY",
      "color": "red",
      "service": "Life-Support",
      "status": "ACTIVE",
      "metrics": {
        "integrity": 90,
        "energy": 1619,
        "temp": 136
      },
      "fw_version": "v10.0"
    },
    {
      "id": "MRS-AI--017",
      "sector": "MARS-COLONY",
      "color": "red",
      "service": "AI-Cortex",
      "status": "ACTIVE",
      "metrics": {
        "integrity": 94,
        "energy": 3837,
        "temp": 285
      },
      "fw_version": "v10.6"
    },
    {
      "id": "MRS-DEF-018",
      "sector": "MARS-COLONY",
      "color": "red",
      "service": "Defense-Grid",
      "status": "ACTIVE",
      "metrics": {
        "integrity": 97,
        "energy": 871,
        "temp": 296
      },
      "fw_version": "v12.6"
    },
    {
      "id": "MRS-AI--019",
      "sector": "MARS-COLONY",
      "color": "red",
      "service": "AI-Cortex",
      "status": "ACTIVE",
      "metrics": {
        "integrity": 97,
        "energy": 4102,
        "temp": 117
      },
      "fw_version": "v12.5"
    },
    {
      "id": "MRS-DEF-020",
      "sector": "MARS-COLONY",
      "color": "red",
      "service": "Defense-Grid",
      "status": "ACTIVE",
      "metrics": {
        "integrity": 95,
        "energy": 1721,
        "temp": 443
      },
      "fw_version": "v11.1"
    },
    {
      "id": "MRS-QUA-021",
      "sector": "MARS-COLONY",
      "color": "red",
      "service": "Quantum-Net",
      "status": "ACTIVE",
      "metrics": {
        "integrity": 100,
        "energy": 2211,
        "temp": 761
      },
      "fw_version": "v12.3"
    },
    {
      "id": "TTN-QUA-000",
      "sector": "TITAN-OUTPOST",
      "color": "yellow",
      "service": "Quantum-Net",
      "status": "ACTIVE",
      "metrics": {
        "integrity": 92,
        "energy": 4619,
        "temp": 846
      },
      "fw_version": "v11.2"
    },
    {
      "id": "TTN-LIF-001",
      "sector": "TITAN-OUTPOST",
      "color": "yellow",
      "service": "Life-Support",
      "status": "ACTIVE",
      "metrics": {
        "integrity": 92,
        "energy": 219,
        "temp": 308
      },
      "fw_version": "v12.9"
    },
    {
      "id": "TTN-FUS-002",
      "sector": "TITAN-OUTPOST",
      "color": "yellow",
      "service": "Fusion-Reactor",
      "status": "ACTIVE",
      "metrics": {
        "integrity": 98,
        "energy": 2805,
        "temp": 184
      },
      "fw_version": "v12.1"
    },
    {
      "id": "TTN-AI--003",
      "sector": "TITAN-OUTPOST",
      "color": "yellow",
      "service": "AI-Cortex",
      "status": "ACTIVE",
      "metrics": {
        "integrity": 91,
        "energy": 2522,
        "temp": 660
      },
      "fw_version": "v10.6"
    },
    {
      "id": "TTN-FUS-004",
      "sector": "TITAN-OUTPOST",
      "color": "yellow",
      "service": "Fusion-Reactor",
      "status": "ACTIVE",
      "metrics": {
        "integrity": 94,
        "energy": 4952,
        "temp": 625
      },
      "fw_version": "v10.7"
    },
    {
      "id": "TTN-DEF-005",
      "sector": "TITAN-OUTPOST",
      "color": "yellow",
      "service": "Defense-Grid",
      "status": "ACTIVE",
      "metrics": {
        "integrity": 99,
        "energy": 2980,
        "temp": 128
      },
      "fw_version": "v11.9"
    },
    {
      "id": "TTN-DEF-006",
      "sector": "TITAN-OUTPOST",
      "color": "yellow",
      "service": "Defense-Grid",
      "status": "ACTIVE",
      "metrics": {
        "integrity": 91,
        "energy": 718,
        "temp": 203
      },
      "fw_version": "v11.2"
    },
    {
      "id": "TTN-AI--007",
      "sector": "TITAN-OUTPOST",
      "color": "yellow",
      "service": "AI-Cortex",
      "status": "ACTIVE",
      "metrics": {
        "integrity": 90,
        "energy": 659,
        "temp": 488
      },
      "fw_version": "v11.0"
    },
    {
      "id": "TTN-QUA-008",
      "sector": "TITAN-OUTPOST",
      "color": "yellow",
      "service": "Quantum-Net",
      "status": "ACTIVE",
      "metrics": {
        "integrity": 100,
        "energy": 3420,
        "temp": 826
      },
      "fw_version": "v11.2"
    },
    {
      "id": "TTN-DEF-009",
      "sector": "TITAN-OUTPOST",
      "color": "yellow",
      "service": "Defense-Grid",
      "status": "ACTIVE",
      "metrics": {
        "integrity": 100,
        "energy": 772,
        "temp": 213
      },
      "fw_version": "v12.8"
    },
    {
      "id": "TTN-FUS-010",
      "sector": "TITAN-OUTPOST",
      "color": "yellow",
      "service": "Fusion-Reactor",
      "status": "ACTIVE",
      "metrics": {
        "integrity": 99,
        "energy": 2866,
        "temp": 713
      },
      "fw_version": "v12.2"
    },
    {
      "id": "TTN-DEF-011",
      "sector": "TITAN-OUTPOST",
      "color": "yellow",
      "service": "Defense-Grid",
      "status": "ACTIVE",
      "metrics": {
        "integrity": 90,
        "energy": 4063,
        "temp": 817
      },
      "fw_version": "v12.9"
    },
    {
      "id": "TTN-AI--012",
      "sector": "TITAN-OUTPOST",
      "color": "yellow",
      "service": "AI-Cortex",
      "status": "ACTIVE",
      "metrics": {
        "integrity": 97,
        "energy": 4355,
        "temp": 489
      },
      "fw_version": "v10.3"
    },
    {
      "id": "TTN-AI--013",
      "sector": "TITAN-OUTPOST",
      "color": "yellow",
      "service": "AI-Cortex",
      "status": "ACTIVE",
      "metrics": {
        "integrity": 94,
        "energy": 4993,
        "temp": 818
      },
      "fw_version": "v11.6"
    },
    {
      "id": "TTN-QUA-014",
      "sector": "TITAN-OUTPOST",
      "color": "yellow",
      "service": "Quantum-Net",
      "status": "ACTIVE",
      "metrics": {
        "integrity": 96,
        "energy": 3863,
        "temp": 453
      },
      "fw_version": "v11.5"
    },
    {
      "id": "TTN-LIF-015",
      "sector": "TITAN-OUTPOST",
      "color": "yellow",
      "service": "Life-Support",
      "status": "ACTIVE",
      "metrics": {
        "integrity": 95,
        "energy": 1350,
        "temp": 165
      },
      "fw_version": "v10.0"
    },
    {
      "id": "TTN-AI--016",
      "sector": "TITAN-OUTPOST",
      "color": "yellow",
      "service": "AI-Cortex",
      "status": "ACTIVE",
      "metrics": {
        "integrity": 91,
        "energy": 3967,
        "temp": 207
      },
      "fw_version": "v12.6"
    },
    {
      "id": "TTN-FUS-017",
      "sector": "TITAN-OUTPOST",
      "color": "yellow",
      "service": "Fusion-Reactor",
      "status": "ACTIVE",
      "metrics": {
        "integrity": 99,
        "energy": 2437,
        "temp": 294
      },
      "fw_version": "v12.0"
    },
    {
      "id": "TTN-QUA-018",
      "sector": "TITAN-OUTPOST",
      "color": "yellow",
      "service": "Quantum-Net",
      "status": "CRITICAL",
      "metrics": {
        "integrity": 53,
        "energy": 1871,
        "temp": 299
      },
      "fw_version": "v11.5"
    },
    {
      "id": "TTN-QUA-019",
      "sector": "TITAN-OUTPOST",
      "color": "yellow",
      "service": "Quantum-Net",
      "status": "ACTIVE",
      "metrics": {
        "integrity": 99,
        "energy": 2922,
        "temp": 648
      },
      "fw_version": "v10.3"
    },
    {
      "id": "TTN-FUS-020",
      "sector": "TITAN-OUTPOST",
      "color": "yellow",
      "service": "Fusion-Reactor",
      "status": "ACTIVE",
      "metrics": {
        "integrity": 92,
        "energy": 1112,
        "temp": 571
      },
      "fw_version": "v12.2"
    },
    {
      "id": "TTN-DEF-021",
      "sector": "TITAN-OUTPOST",
      "color": "yellow",
      "service": "Defense-Grid",
      "status": "ACTIVE",
      "metrics": {
        "integrity": 94,
        "energy": 2534,
        "temp": 221
      },
      "fw_version": "v10.3"
    },
    {
      "id": "TTN-AI--022",
      "sector": "TITAN-OUTPOST",
      "color": "yellow",
      "service": "AI-Cortex",
      "status": "ACTIVE",
      "metrics": {
        "integrity": 100,
        "energy": 4355,
        "temp": 802
      },
      "fw_version": "v11.4"
    },
    {
      "id": "TTN-QUA-023",
      "sector": "TITAN-OUTPOST",
      "color": "yellow",
      "service": "Quantum-Net",
      "status": "ACTIVE",
      "metrics": {
        "integrity": 95,
        "energy": 299,
        "temp": 881
      },
      "fw_version": "v11.7"
    },
    {
      "id": "TTN-AI--024",
      "sector": "TITAN-OUTPOST",
      "color": "yellow",
      "service": "AI-Cortex",
      "status": "ACTIVE",
      "metrics": {
        "integrity": 91,
        "energy": 3072,
        "temp": 862
      },
      "fw_version": "v11.8"
    },
    {
      "id": "TTN-FUS-025",
      "sector": "TITAN-OUTPOST",
      "color": "yellow",
      "service": "Fusion-Reactor",
      "status": "ACTIVE",
      "metrics": {
        "integrity": 95,
        "energy": 3191,
        "temp": 798
      },
      "fw_version": "v10.2"
    },
    {
      "id": "TTN-AI--026",
      "sector": "TITAN-OUTPOST",
      "color": "yellow",
      "service": "AI-Cortex",
      "status": "ACTIVE",
      "metrics": {
        "integrity": 100,
        "energy": 3034,
        "temp": 670
      },
      "fw_version": "v12.2"
    },
    {
      "id": "TTN-DEF-027",
      "sector": "TITAN-OUTPOST",
      "color": "yellow",
      "service": "Defense-Grid",
      "status": "ACTIVE",
      "metrics": {
        "integrity": 90,
        "energy": 1791,
        "temp": 164
      },
      "fw_version": "v12.4"
    },
    {
      "id": "ORB-LIF-000",
      "sector": "ORBITAL-STATION",
      "color": "cyan",
      "service": "Life-Support",
      "status": "ACTIVE",
      "metrics": {
        "integrity": 97,
        "energy": 672,
        "temp": 795
      },
      "fw_version": "v12.8"
    },
    {
      "id": "ORB-DEF-001",
      "sector": "ORBITAL-STATION",
      "color": "cyan",
      "service": "Defense-Grid",
      "status": "ACTIVE",
      "metrics": {
        "integrity": 95,
        "energy": 3908,
        "temp": 445
      },
      "fw_version": "v11.1"
    },
    {
      "id": "ORB-FUS-002",
      "sector": "ORBITAL-STATION",
      "color": "cyan",
      "service": "Fusion-Reactor",
      "status": "ACTIVE",
      "metrics": {
        "integrity": 96,
        "energy": 4832,
        "temp": 579
      },
      "fw_version": "v10.9"
    },
    {
      "id": "ORB-FUS-003",
      "sector": "ORBITAL-STATION",
      "color": "cyan",
      "service": "Fusion-Reactor",
      "status": "ACTIVE",
      "metrics": {
        "integrity": 100,
        "energy": 996,
        "temp": 231
      },
      "fw_version": "v11.1"
    },
    {
      "id": "ORB-FUS-004",
      "sector": "ORBITAL-STATION",
      "color": "cyan",
      "service": "Fusion-Reactor",
      "status": "ACTIVE",
      "metrics": {
        "integrity": 95,
        "energy": 540,
        "temp": 812
      },
      "fw_version": "v12.5"
    },
    {
      "id": "ORB-AI--005",
      "sector": "ORBITAL-STATION",
      "color": "cyan",
      "service": "AI-Cortex",
      "status": "ACTIVE",
      "metrics": {
        "integrity": 100,
        "energy": 3123,
        "temp": 314
      },
      "fw_version": "v10.2"
    },
    {
      "id": "ORB-AI--006",
      "sector": "ORBITAL-STATION",
      "color": "cyan",
      "service": "AI-Cortex",
      "status": "CRITICAL",
      "metrics": {
        "integrity": 68,
        "energy": 4466,
        "temp": 558
      },
      "fw_version": "v11.5"
    },
    {
      "id": "ORB-QUA-007",
      "sector": "ORBITAL-STATION",
      "color": "cyan",
      "service": "Quantum-Net",
      "status": "ACTIVE",
      "metrics": {
        "integrity": 93,
        "energy": 575,
        "temp": 847
      },
      "fw_version": "v11.1"
    },
    {
      "id": "ORB-LIF-008",
      "sector": "ORBITAL-STATION",
      "color": "cyan",
      "service": "Life-Support",
      "status": "ACTIVE",
      "metrics": {
        "integrity": 94,
        "energy": 4591,
        "temp": 679
      },
      "fw_version": "v10.4"
    },
    {
      "id": "ORB-QUA-009",
      "sector": "ORBITAL-STATION",
      "color": "cyan",
      "service": "Quantum-Net",
      "status": "CRITICAL",
      "metrics": {
        "integrity": 68,
        "energy": 2990,
        "temp": 115
      },
      "fw_version": "v11.5"
    },
    {
      "id": "ORB-DEF-010",
      "sector": "ORBITAL-STATION",
      "color": "cyan",
      "service": "Defense-Grid",
      "status": "ACTIVE",
      "metrics": {
        "integrity": 92,
        "energy": 4467,
        "temp": 719
      },
      "fw_version": "v10.0"
    },
    {
      "id": "ORB-AI--011",
      "sector": "ORBITAL-STATION",
      "color": "cyan",
      "service": "AI-Cortex",
      "status": "ACTIVE",
      "metrics": {
        "integrity": 90,
        "energy": 2238,
        "temp": 330
      },
      "fw_version": "v11.0"
    },
    {
      "id": "ORB-LIF-012",
      "sector": "ORBITAL-STATION",
      "color": "cyan",
      "service": "Life-Support",
      "status": "ACTIVE",
      "metrics": {
        "integrity": 91,
        "energy": 3388,
        "temp": 780
      },
      "fw_version": "v11.0"
    },
    {
      "id": "ORB-DEF-013",
      "sector": "ORBITAL-STATION",
      "color": "cyan",
      "service": "Defense-Grid",
      "status": "ACTIVE",
      "metrics": {
        "integrity": 96,
        "energy": 499,
        "temp": 420
      },
      "fw_version": "v11.1"
    },
    {
      "id": "ORB-LIF-014",
      "sector": "ORBITAL-STATION",
      "color": "cyan",
      "service": "Life-Support",
      "status": "ACTIVE",
      "metrics": {
        "integrity": 98,
        "energy": 4340,
        "temp": 719
      },
      "fw_version": "v12.3"
    },
    {
      "id": "ORB-AI--015",
      "sector": "ORBITAL-STATION",
      "color": "cyan",
      "service": "AI-Cortex",
      "status": "ACTIVE",
      "metrics": {
        "integrity": 90,
        "energy": 1096,
        "temp": 622
      },
      "fw_version": "v12.6"
    },
    {
      "id": "ORB-LIF-016",
      "sector": "ORBITAL-STATION",
      "color": "cyan",
      "service": "Life-Support",
      "status": "ACTIVE",
      "metrics": {
        "integrity": 99,
        "energy": 1428,
        "temp": 518
      },
      "fw_version": "v10.9"
    },
    {
      "id": "ORB-AI--017",
      "sector": "ORBITAL-STATION",
      "color": "cyan",
      "service": "AI-Cortex",
      "status": "ACTIVE",
      "metrics": {
        "integrity": 94,
        "energy": 3378,
        "temp": 227
      },
      "fw_version": "v10.1"
    },
    {
      "id": "ORB-DEF-018",
      "sector": "ORBITAL-STATION",
      "color": "cyan",
      "service": "Defense-Grid",
      "status": "ACTIVE",
      "metrics": {
        "integrity": 98,
        "energy": 2061,
        "temp": 638
      },
      "fw_version": "v12.8"
    },
    {
      "id": "ORB-FUS-019",
      "sector": "ORBITAL-STATION",
      "color": "cyan",
      "service": "Fusion-Reactor",
      "status": "ACTIVE",
      "metrics": {
        "integrity": 100,
        "energy": 517,
        "temp": 414
      },
      "fw_version": "v12.9"
    },
    {
      "id": "ORB-AI--020",
      "sector": "ORBITAL-STATION",
      "color": "cyan",
      "service": "AI-Cortex",
      "status": "ACTIVE",
      "metrics": {
        "integrity": 97,
        "energy": 4777,
        "temp": 430
      },
      "fw_version": "v11.0"
    },
    {
      "id": "ORB-AI--021",
      "sector": "ORBITAL-STATION",
      "color": "cyan",
      "service": "AI-Cortex",
      "status": "ACTIVE",
      "metrics": {
        "integrity": 98,
        "energy": 1611,
        "temp": 136
      },
      "fw_version": "v10.3"
    },
    {
      "id": "ORB-DEF-022",
      "sector": "ORBITAL-STATION",
      "color": "cyan",
      "service": "Defense-Grid",
      "status": "ACTIVE",
      "metrics": {
        "integrity": 91,
        "energy": 3074,
        "temp": 879
      },
      "fw_version": "v12.3"
    },
    {
      "id": "ORB-AI--023",
      "sector": "ORBITAL-STATION",
      "color": "cyan",
      "service": "AI-Cortex",
      "status": "ACTIVE",
      "metrics": {
        "integrity": 93,
        "energy": 4903,
        "temp": 473
      },
      "fw_version": "v10.9"
    },
    {
      "id": "ORB-AI--024",
      "sector": "ORBITAL-STATION",
      "color": "cyan",
      "service": "AI-Cortex",
      "status": "ACTIVE",
      "metrics": {
        "integrity": 96,
        "energy": 4307,
        "temp": 814
      },
      "fw_version": "v12.2"
    },
    {
      "id": "ORB-DEF-025",
      "sector": "ORBITAL-STATION",
      "color": "cyan",
      "service": "Defense-Grid",
      "status": "ACTIVE",
      "metrics": {
        "integrity": 98,
        "energy": 2394,
        "temp": 639
      },
      "fw_version": "v11.4"
    },
    {
      "id": "ORB-LIF-026",
      "sector": "ORBITAL-STATION",
      "color": "cyan",
      "service": "Life-Support",
      "status": "ACTIVE",
      "metrics": {
        "integrity": 93,
        "energy": 160,
        "temp": 866
      },
      "fw_version": "v12.3"
    },
    {
      "id": "ORB-AI--027",
      "sector": "ORBITAL-STATION",
      "color": "cyan",
      "service": "AI-Cortex",
      "status": "ACTIVE",
      "metrics": {
        "integrity": 92,
        "energy": 1354,
        "temp": 364
      },
      "fw_version": "v11.7"
    }
  ],
  "global_integrity": 96
}